libPy2023/__init__.py
libPy2023/libPy2023.py
libPy2023/setup.py
libPy2023-2023.1010.1440.dist-info/METADATA
libPy2023-2023.1010.1440.dist-info/WHEEL
libPy2023-2023.1010.1440.dist-info/top_level.txt
libPy2023-2023.1010.1440.dist-info/RECORD
